sphinx_runpython/__init__.py
sphinx_runpython/__main__.py
sphinx_runpython/_cmd_helper.py
sphinx_runpython/conf_helper.py
sphinx_runpython/convert.py
sphinx_runpython/ext_helper.py
sphinx_runpython/ext_io_helper.py
sphinx_runpython/ext_test_case.py
sphinx_runpython/github_link.py
sphinx_runpython/import_object_helper.py
sphinx_runpython/language.py
sphinx_runpython/process_rst.py
sphinx_runpython/readme.py
sphinx_runpython/sphinx_rst_builder.py
sphinx_runpython/blocdefs/__init__.py
sphinx_runpython/blocdefs/sphinx_blocref_extension.py
sphinx_runpython/blocdefs/sphinx_exref_extension.py
sphinx_runpython/blocdefs/sphinx_faqref_extension.py
sphinx_runpython/blocdefs/sphinx_mathdef_extension.py
sphinx_runpython/collapse/__init__.py
sphinx_runpython/collapse/sphinx_collapse_extension.py
sphinx_runpython/docassert/__init__.py
sphinx_runpython/docassert/sphinx_docassert_extension.py
sphinx_runpython/epkg/__init__.py
sphinx_runpython/epkg/sphinx_epkg_extension.py
sphinx_runpython/gdot/__init__.py
sphinx_runpython/gdot/sphinx_gdot_extension.py
sphinx_runpython/quote/__init__.py
sphinx_runpython/quote/sphinx_quote_extension.py
sphinx_runpython/runpython/__init__.py
sphinx_runpython/runpython/run_cmd.py
sphinx_runpython/runpython/sphinx_runpython_extension.py
sphinx_runpython/tools/__init__.py
sphinx_runpython/tools/img_export.py
sphinx_runpython/tools/latex_functions.py
sphinx_runpython/tools/sphinx_api.py
sphinx_runpython-0.3.0.dist-info/LICENSE.txt
sphinx_runpython-0.3.0.dist-info/METADATA
sphinx_runpython-0.3.0.dist-info/WHEEL
sphinx_runpython-0.3.0.dist-info/top_level.txt
sphinx_runpython-0.3.0.dist-info/RECORD
