Metadata-Version: 2.1
Name: sphinx-runpython
Version: 0.3.0
Summary: Run python code in sphinx
Home-page: https://github.com/sdpython/sphinx-runpython
Author: Xavier Dupré
Author-email: xavier.dupre@gmail.com
Classifier: Intended Audience :: Science/Research
Classifier: Intended Audience :: Developers
Classifier: License :: OSI Approved :: MIT License
Classifier: Programming Language :: C
Classifier: Programming Language :: Python
Classifier: Topic :: Software Development
Classifier: Topic :: Scientific/Engineering
Classifier: Development Status :: 5 - Production/Stable
Classifier: Operating System :: Microsoft :: Windows
Classifier: Operating System :: POSIX
Classifier: Operating System :: Unix
Classifier: Operating System :: MacOS
Classifier: Programming Language :: Python :: 3
License-File: LICENSE.txt
Requires-Dist: sphinx
